setup.py
redact/__init__.py
redact/redact.py
redact.egg-info/PKG-INFO
redact.egg-info/SOURCES.txt
redact.egg-info/dependency_links.txt
redact.egg-info/entry_points.txt
redact.egg-info/pbr.json
redact.egg-info/requires.txt
redact.egg-info/top_level.txt