Metadata-Version: 1.0
Name: redact
Version: 0.1.1
Summary: rendering config files from templates
Home-page: https://github.com/zweifisch/redact
Author: Feng Zhou
Author-email: zf.pascal@gmail.com
License: UNKNOWN
Platform: UNKNOWN
